config/__init__.py
config/class.py
config/main.py
config/types.py
config/utils.py
config/search_space/__init__.py
config/search_space/main.py
configbase-0.0.1.dist-info/METADATA
configbase-0.0.1.dist-info/WHEEL
configbase-0.0.1.dist-info/top_level.txt
configbase-0.0.1.dist-info/RECORD
