Metadata-Version: 2.1
Name: configbase
Version: 0.0.1
Summary: A Typed, Compositional Configuration Library
Author-email: Iordanis Fostiropoulos <mail@iordanis.me>
License: proprietary
Project-URL: homepage, https://iordanis.me
Requires-Python: >=3.10
Requires-Dist: numpy
Provides-Extra: dev
Requires-Dist: mypy ; extra == 'dev'
Requires-Dist: flake8 ; extra == 'dev'
Requires-Dist: pytest ; extra == 'dev'
Requires-Dist: black ; extra == 'dev'
Requires-Dist: pylint ; extra == 'dev'
Requires-Dist: codecov-cli ; extra == 'dev'
Requires-Dist: pytest-cov ; extra == 'dev'
Requires-Dist: pytest-xdist ; extra == 'dev'
Requires-Dist: types-PyYAML ; extra == 'dev'
